pyfirebasestockscli/__init__.py
pyfirebasestockscli/__main__.py
pyfirebasestockscli/dividend_kings.py
pyfirebasestockscli-1.0.7.dist-info/LICENSE
pyfirebasestockscli-1.0.7.dist-info/METADATA
pyfirebasestockscli-1.0.7.dist-info/WHEEL
pyfirebasestockscli-1.0.7.dist-info/entry_points.txt
pyfirebasestockscli-1.0.7.dist-info/top_level.txt
pyfirebasestockscli-1.0.7.dist-info/RECORD
