Metadata-Version: 2.1
Name: pyfirebasestockscli
Version: 1.0.7
Summary: portfolio+ command line interface for firebase operations.
Home-page: https://github.com/SlashGordon/pyfirebasestockscli
Author: Slash Gordon
Author-email: slash.gordon.dev@gmail.com
License: UNKNOWN
Platform: UNKNOWN
Classifier: Development Status :: 5 - Production/Stable
Classifier: Intended Audience :: Developers
Classifier: Natural Language :: English
Classifier: License :: OSI Approved :: MIT License
Classifier: Operating System :: OS Independent
Classifier: Programming Language :: Python
Classifier: Programming Language :: Python :: 3.6
Classifier: Topic :: Software Development :: Libraries :: Python Modules
Requires-Dist: firebase-admin (==4.3.0)
Requires-Dist: pystockfilter (>=1.0.6)
